{  
  "openapi":"3.0.0",
  "info":{  
     "title":"History",
     "version":"0.0.1"
  },
  "servers":[  
     {  
        "url":"http://127.0.0.1:8888/v1/history"
     }
  ],
  "components":{  
     "securitySchemes":{  

     },
     "schemas":{  

     }
  },
  "security":[  
     {  

     }
  ],
  "paths":{  
     "/get_transaction":{  
        "post":{  
           "tags":[  

           ],
           "summary":"get_transaction",
           "description":"",
           "operationId":"get_transaction-1",
           "parameters":[  

           ],
           "requestBody":{  
              "content":{  
                 "application/json":{  
                    "schema":{  
                       "type":"object",
                       "properties":{  
                          "id":{  
                             "type":"string",
                             "description":""
                          }
                       }
                    }
                 }
              }
           },
           "deprecated":false
        }
     },
     "/get_actions":{  
        "post":{  
           "tags":[  

           ],
           "summary":"get_actions",
           "description":"",
           "operationId":"get_actions-1",
           "parameters":[  

           ],
           "requestBody":{  
              "content":{  
                 "application/json":{  
                    "schema":{  
                       "type":"object",
                       "properties":{  
                          "pos":{  
                             "type":"integer",
                             "description":"",
                             "format":"int32"
                          },
                          "offset":{  
                             "type":"integer",
                             "description":"",
                             "format":"int32"
                          },
                          "account_name":{  
                             "type":"string",
                             "description":""
                          }
                       }
                    }
                 }
              }
           },
           "deprecated":false
        }
     },
     "/get_key_accounts":{  
        "post":{  
           "tags":[  

           ],
           "summary":"get_key_accounts",
           "description":"",
           "operationId":"get_key_accounts-1",
           "parameters":[  

           ],
           "requestBody":{  
              "content":{  
                 "application/json":{  
                    "schema":{  
                       "type":"object",
                       "properties":{  
                          "public_key":{  
                             "type":"string",
                             "description":""
                          }
                       }
                    }
                 }
              }
           },
           "deprecated":false
        }
     },
     "/get_controlled_accounts":{  
        "post":{  
           "tags":[  

           ],
           "summary":"get_controlled_accounts",
           "description":"",
           "operationId":"get_controlled_accounts-1",
           "parameters":[  

           ],
           "requestBody":{  
              "content":{  
                 "application/json":{  
                    "schema":{  
                       "type":"object",
                       "properties":{  
                          "controlling_account":{  
                             "type":"string",
                             "description":""
                          }
                       }
                    }
                 }
              }
           },
           "deprecated":false
        }
     }
  },
  "x-headers":[  
     {  
        "value":"application/x-www-form-urlencoded; charset=UTF-8",
        "key":"Content-Type"
     }
  ],
  "x-explorer-enabled":true,
  "x-proxy-enabled":false,
  "x-samples-enabled":true,
  "x-samples-languages":[  
     "curl",
     "node",
     "ruby",
     "javascript",
     "python"
  ]
}
